{
  "taskList": [
    {
      "id": "TID-1",
      "title": "Make Presentation",
      "status": "Uninitiated",
      "assignedMember": "Team Member 2",
      "dueDate": "2024-10-06",
      "isAssigned": "Yes",
      "estimatedHours": "13:16",
      "priorityType": "Low",
      "creationDate": "2024-10-10"
    },
    {
      "id": "TID-2",
      "title": "Brief Client",
      "status": "In Progress",
      "assignedMember": "Team Member 1",
      "dueDate": "2024-10-12",
      "isAssigned": "Yes",
      "estimatedHours": "08:30",
      "priorityType": "High",
      "creationDate": "2024-10-09"
    },
    {
      "id": "TID-3",
      "title": "Debug Code",
      "status": "Completed",
      "assignedMember": "Team Member 3",
      "dueDate": "2024-10-15",
      "isAssigned": "No",
      "estimatedHours": "05:00",
      "priorityType": "Medium",
      "creationDate": "2024-10-08"
    },
    {
      "id": "TID-4",
      "title": "Code Evaluation",
      "status": "Uninitiated",
      "assignedMember": "Team Member 2",
      "dueDate": "2024-10-13",
      "isAssigned": "Yes",
      "estimatedHours": "17:37",
      "priorityType": "Medium",
      "creationDate": "2024-10-12"
    },
    {
      "id": "TID-5",
      "title": "New Updated Task",
      "status": "N/A",
      "assignedMember": "N/A",
      "dueDate": "2024-10-13",
      "isAssigned": "N/A",
      "estimatedHours": "04:30",
      "priorityType": "Medium",
      "creationDate": "2024-10-12"
    }
  ]
}